tkhelper/__init__.py
tkhelper/package_info.py
tkhelper/py.typed
tkhelper/widgets.py
tkhelper/progressbars/__init__.py
tkhelper/progressbars/circular.py
tkhelper-2.1.1.dist-info/LICENSE
tkhelper-2.1.1.dist-info/METADATA
tkhelper-2.1.1.dist-info/WHEEL
tkhelper-2.1.1.dist-info/top_level.txt
tkhelper-2.1.1.dist-info/RECORD
