Metadata-Version: 2.1
Name: tkhelper
Version: 2.1.1
Summary: A module to display some customized tkinter modules
Author-email: Erdogan Onal <erdoganonal@windowslive.com>
Project-URL: Homepage, https://github.com/erdoganonal/tk_helper
Project-URL: Bug Tracker, https://github.com/erdoganonal/tk_helper/issues
Classifier: Programming Language :: Python :: 3
Classifier: License :: OSI Approved :: MIT License
Classifier: Operating System :: OS Independent
Requires-Python: >=3.6
License-File: LICENSE
Requires-Dist: colour >=0.1.5
Requires-Dist: pillow >=10.3.0
